cubicweb_skos/__init__.py
cubicweb_skos/__pkginfo__.py
cubicweb_skos/ccplugin.py
cubicweb_skos/dataimport.py
cubicweb_skos/entities.py
cubicweb_skos/hooks.py
cubicweb_skos/lcsv.py
cubicweb_skos/rdfio.py
cubicweb_skos/schema.py
cubicweb_skos/site_cubicweb.py
cubicweb_skos/sobjects.py
cubicweb_skos/i18n/en.po
cubicweb_skos/i18n/fr.po
cubicweb_skos/i18n/static-messages.pot
cubicweb_skos/migration/0.10.0_Any.py
cubicweb_skos/migration/0.12.1_Any.py
cubicweb_skos/migration/0.2.0_Any.py
cubicweb_skos/migration/0.4.0_Any.py
cubicweb_skos/migration/0.5.0_Any.py
cubicweb_skos/migration/0.6.0_Any.py
cubicweb_skos/migration/0.7.2_Any.py
cubicweb_skos/migration/3.1.0_Any.py
cubicweb_skos/views/__init__.py
cubicweb_skos/views/rdf.py
cubicweb_skos/views/widgets.py
cubicweb_skos-3.1.0.dist-info/METADATA
cubicweb_skos-3.1.0.dist-info/WHEEL
cubicweb_skos-3.1.0.dist-info/entry_points.txt
cubicweb_skos-3.1.0.dist-info/top_level.txt
cubicweb_skos-3.1.0.dist-info/RECORD
