Metadata-Version: 2.1
Name: cubicweb-skos
Version: 3.1.0
Summary: "SKOS implementation for cubicweb"
Home-page: https://forge.extranet.logilab.fr/cubicweb/cubes/cubicweb-skos
Author: LOGILAB S.A. (Paris, FRANCE)
Author-email: contact@logilab.fr
License: LGPL
Classifier: Environment :: Web Environment
Classifier: Framework :: CubicWeb
Classifier: Programming Language :: Python
Classifier: Programming Language :: Python :: 3
Classifier: Programming Language :: JavaScript
Requires-Dist: cubicweb <5.0.0,>=4.0.0
Requires-Dist: cubicweb-web <2.0.0,>=1.0.0
